xcollection/__init__.py
xcollection/main.py
xcollection/types.py
xcollection-2021.12.23.dist-info/LICENSE
xcollection-2021.12.23.dist-info/METADATA
xcollection-2021.12.23.dist-info/WHEEL
xcollection-2021.12.23.dist-info/top_level.txt
xcollection-2021.12.23.dist-info/RECORD
