Metadata-Version: 2.1
Name: xcollection
Version: 2021.12.23
Summary: A high-level mapping of name/key to Xarray.Datasets.
Home-page: https://github.com/NCAR/xcollection
Maintainer: Xdev
Maintainer-email: xdev@ucar.edu
License: Apache Software License 2.0
Project-URL: Documentation, https://github.com/NCAR/xcollection
Project-URL: Source, https://github.com/NCAR/xcollection
Project-URL: Tracker, https://github.com/NCAR/xcollection/issues
Keywords: xarray
Platform: UNKNOWN
Classifier: Development Status :: 2 - Pre-Alpha
Classifier: License :: OSI Approved :: Apache Software License
Classifier: Natural Language :: English
Classifier: Programming Language :: Python :: 3
Classifier: Programming Language :: Python :: 3.7
Classifier: Programming Language :: Python :: 3.8
Classifier: Programming Language :: Python :: 3.9
Classifier: Topic :: Scientific/Engineering
Classifier: Operating System :: OS Independent
Classifier: Intended Audience :: Science/Research
Requires-Python: >=3.7
License-File: LICENSE
Requires-Dist: pydantic
Requires-Dist: xarray
Requires-Dist: toolz
